{"chunk_definitions":[{"row":11,"row_count":1,"visible":true,"expansion_state":0,"options":{"engine":"r","label":"unnamed-chunk-243"},"document_id":"310D3802","chunk_id":"cqhen4m5ioqll","chunk_label":"unnamed-chunk-1"},{"row":15,"row_count":1,"visible":true,"expansion_state":0,"options":{"engine":"r","label":"unnamed-chunk-244"},"document_id":"310D3802","chunk_id":"cy34i4myfjd8c","chunk_label":"unnamed-chunk-2"},{"row":34,"row_count":1,"visible":true,"expansion_state":0,"options":{"engine":"r","label":"unnamed-chunk-250"},"document_id":"310D3802","chunk_id":"cqo957pb9gxz4","chunk_label":"unnamed-chunk-3"},{"row":39,"row_count":1,"visible":true,"expansion_state":0,"options":{"engine":"r","label":"unnamed-chunk-247"},"document_id":"310D3802","chunk_id":"chu0a78z4auzq","chunk_label":"unnamed-chunk-4"}],"doc_write_time":1599482821}